{
    "skills": {
        "professional": {
            "languages": {
                "icon": "code",
                "data": [
                    {
                        "name": "PHP",
                        "icon": ["fab", "php"],
                        "rating": 9
                    },
                    {
                        "name": "JavaScript",
                        "icon": ["fab", "js"],
                        "rating": 9
                    },
                    {
                        "name": "HTML5",
                        "icon": ["fab", "html5"],
                        "rating": 9
                    },
                    {
                        "name": "CSS3",
                        "icon": ["fab", "css3-alt"],
                        "rating": 7
                    }
                ]
            },
            "database": {
                "icon": "database",
                "data": [
                    {
                        "name": "MySQL",
                        "image": "dbs_mysql.png",
                        "rating": 8
                    },
                    {
                        "name": "PostgreSQL",
                        "image": "dbs_postgresql.png",
                        "rating": 7
                    },
                    {
                        "name": "SQLite",
                        "image": "dbs_sqlite.png",
                        "rating": 8
                    }
                ]
            },
            "Frameworks / Libraries": {
                "icon": "coffee",
                "data": [
                    {
                        "name": "Laravel",
                        "icon": ["fab", "laravel"],
                        "rating": 9
                    },
                    {
                        "name": "CodeIgnitor",
                        "image": "codeigniter.svg",
                        "rating": 6
                    },
                    {
                        "name": "AngularJS",
                        "icon": ["fab", "angular"],
                        "rating": 9
                    },
                    {
                        "name": "Ionic 1",
                        "image": "ionic.svg",
                        "rating": 8
                    },
                    {
                        "name": "React",
                        "icon": ["fab", "react"],
                        "rating": 7
                    },
                    {
                        "name": "Node.js",
                        "icon": ["fab", "node"],
                        "rating": 4
                    }
                ]
            },
            "Tools": {
                "icon": "wrench",
                "data": [
                    {
                        "name": "Gulp",
                        "icon": ["fab", "gulp"],
                        "rating": 9
                    },
                    {
                        "name": "Webpack",
                        "rating": 6
                    },
                    {
                        "name": "Git",
                        "rating": 7
                    }
                ]
            },
            "Other": {
                "icon": "fire",
                "data": [
                    {
                        "name": "Linux / OSX / Ubuntu / CentOS",
                        "rating": 6
                    },
                    {
                        "name": "Photoshop",
                        "rating": 4
                    }
                ]
            }
        },
        "personal": {
            "Generals": {
                "icon": "bolt",
                "data": [
                    {
                        "name": "Creativity",
                        "rating": 9
                    },
                    {
                        "name": "Team work",
                        "rating": 9
                    },
                    {
                        "name": "Communication",
                        "rating": 9
                    },
                    {
                        "name": "Hard work",
                        "rating": 9
                    }
                ]
            },
            "Languages": {
                "icon": "language",
                "data": [
                    {
                        "name": "English (Daily use)",
                        "rating": 8
                    },
                    {
                        "name": "Chinese (Native)",
                        "rating": 9
                    }
                ]
            }
        }
    },
    "experiences": [
        {
            "jobTitle": "Software Developer",
            "type": "Permanent",
            "company": "WSP | Opus",
            "url": "http://wsp-opus.co.nz",
            "startDate": "2015-10-27",
            "description": [
                "Develop, maintain and improve upon databases for various internal and external applications.",
                "Analyse existing applications or works to formulate logic for new applications, devises logic procedures, prepares flowcharting, performs coding, data analysis, and tests/debugs programs through the application of professional programming concepts.",
                "Design, develop, modify and evaluate web-based applications.",
                "Liaise with other members in the NZ IT team to assist in resolving problems with software products or software systems.",
                "Provide user support for existing Opus developed applications."
            ]
        },
        {
            "jobTitle": "Web Designer",
            "type": "Permanent",
            "company": "Authenticate (Rebranded from Ecardz)",
            "url": "http://authenticate.co.nz",
            "startDate": "2012-04-24",
            "endDate": "2015-10-26",
            "description": [
                "Developed and keep maintaining Ecardz website (Version 3). Devising SEO strategies.",
                "Designing and developing Quidz hosting platform, web application with Paymark gateway, CandoCard websites, All things horsey and all the other websites, web services and applications.",
                "Designing PVC and business cards.",
                "Design brochure, advertising artworks and writing documentation."
            ]
        },
        {
            "jobTitle": "Web Developer",
            "type": "Conract",
            "company": "Jetlab",
            "url": "http://jetlab.com",
            "startDate": "2012-02-27",
            "endDate": "2012-03-16",
            "description": [
                "Building the website using PHP, MySQL, HTML5, CSS, and JavaScript (JQuery)."
            ]
        },
        {
            "jobTitle": "Web Designer",
            "type": "Short term employment",
            "company": "Authenticate (Rebranded from Ecardz)",
            "url": "http://ecardz.co.nz",
            "startDate": "2011-11-30",
            "endDate": "2011-12-19",
            "description": [
                "Redesigning and rebuiding the website using PHP, XHTML, CSS, JavaScript (JQuery) and Photoshop. All code meets the standard of W3C."
            ]
        },
        {
            "jobTitle": "Technician",
            "type": "Permanent",
            "company": "Huawei Technologies",
            "url": "http://ecardz.co.nz",
            "startDate": "2008-01-01",
            "endDate": "2008-08-01",
            "description": [
                "Team leader in a trail-produce team in charge of the products' distribution and maintenance process, including test, track and problem solving of products, and management of the database of products."
            ]
        }
    ]
}